mps/__init__.py
mps/__main__.py
mps/analysis.py
mps/average.py
mps/czifile.py
mps/load.py
mps/nd2file.py
mps/plotter.py
mps/tifffile.py
mps/utils.py
mps/scripts/__init__.py
mps/scripts/analyze.py
mps/scripts/mps2mp4.py
mps/scripts/phase_plot.py
mps/scripts/split_pacing.py
mps/scripts/summary.py
cardiac_mps-2025.1.0.dist-info/LICENSE
cardiac_mps-2025.1.0.dist-info/LICENSE_czifile
cardiac_mps-2025.1.0.dist-info/LICENSE_nd2file
cardiac_mps-2025.1.0.dist-info/LICENSE_tifffile
cardiac_mps-2025.1.0.dist-info/METADATA
cardiac_mps-2025.1.0.dist-info/WHEEL
cardiac_mps-2025.1.0.dist-info/entry_points.txt
cardiac_mps-2025.1.0.dist-info/top_level.txt
cardiac_mps-2025.1.0.dist-info/RECORD
