Metadata-Version: 2.2
Name: cardiac_mps
Version: 2025.1.0
Summary: Tools for working with caridac mps files
Author-email: Henrik Finsberg <henriknf@simula.no>
License: LGPL-2.1
Project-URL: Homepage, https://github.com/ComputationalPhysiology/mps
Keywords: action potential,cell models,features
Classifier: License :: OSI Approved :: GNU Lesser General Public License v2 (LGPLv2)
Classifier: Programming Language :: Python :: 3
Classifier: Programming Language :: Python :: 3 :: Only
Classifier: Programming Language :: Python :: 3.7
Classifier: Programming Language :: Python :: 3.8
Classifier: Programming Language :: Python :: 3.9
Classifier: Programming Language :: Python :: 3.10
Requires-Python: >=3.7
License-File: LICENSE
License-File: licenses/LICENSE_nd2file
License-File: licenses/LICENSE_czifile
License-File: licenses/LICENSE_tifffile
Requires-Dist: ap-features
Requires-Dist: imageio
Requires-Dist: imageio-ffmpeg
Requires-Dist: matplotlib
Requires-Dist: numpy
Requires-Dist: scipy
Requires-Dist: tifffile
Requires-Dist: typer
Requires-Dist: xmltodict
Provides-Extra: dev
Requires-Dist: Sphinx; extra == "dev"
Requires-Dist: black; extra == "dev"
Requires-Dist: bump-my-version; extra == "dev"
Requires-Dist: flake8; extra == "dev"
Requires-Dist: ipython; extra == "dev"
Requires-Dist: isort; extra == "dev"
Requires-Dist: mypy; extra == "dev"
Requires-Dist: pdbpp; extra == "dev"
Requires-Dist: pip; extra == "dev"
Requires-Dist: pre-commit; extra == "dev"
Requires-Dist: pytest; extra == "dev"
Requires-Dist: pytest-cov; extra == "dev"
Requires-Dist: twine; extra == "dev"
Requires-Dist: types-PyYAML; extra == "dev"
Requires-Dist: wheel; extra == "dev"
Provides-Extra: docs
Requires-Dist: jupyter-book; extra == "docs"
Requires-Dist: jupytext; extra == "docs"
Requires-Dist: sphinxcontrib-bibtex; extra == "docs"
Provides-Extra: motion
Requires-Dist: mps-motion; extra == "motion"
Provides-Extra: test
Requires-Dist: pre-commit; extra == "test"
Requires-Dist: pytest; extra == "test"
Requires-Dist: pytest-cov; extra == "test"
